suoran/__init__.py
suoran/application.py
suoran/common.py
suoran/config.py
suoran/debug.py
suoran/model.py
suoran/route.py
suoran/view.py
suoran/asset/__init__.py
suoran/asset/skeleton.py
suoran/command/__init__.py
suoran/command/action.py
suoran/command/skeleton.py
suoran/command/skeletonzip.py
suoran-0.0.12.dist-info/METADATA
suoran-0.0.12.dist-info/WHEEL
suoran-0.0.12.dist-info/entry_points.txt
suoran-0.0.12.dist-info/license
suoran-0.0.12.dist-info/top_level.txt
suoran-0.0.12.dist-info/RECORD
