Metadata-Version: 2.1
Name: suoran
Version: 0.0.12
Summary: extends sanic
Home-page: https://github.com/chenshenchao/suoran
Author: chenshenchao
Author-email: chenshenchao@outlook.com
License: MIT
Keywords: sanic suoran
Platform: any
Classifier: License :: OSI Approved :: MIT License
Classifier: Intended Audience :: Developers
Classifier: Operating System :: OS Independent
Classifier: Programming Language :: Python :: 3
Classifier: Programming Language :: Python :: 3.7
Classifier: Programming Language :: Python :: 3.8
Classifier: Programming Language :: Python :: 3.9
Requires-Dist: sanic (>=20.9.1)
Requires-Dist: tortoise-orm (>=0.16.16)
Requires-Dist: aiomysql (>=0.0.20)
Requires-Dist: jinja2 (>=2.11.2)
Requires-Dist: python-dotenv (>=0.15.0)
Requires-Dist: ran (>=0.0.4)
